topsis_shubhkarman_102303661/__init__.py
topsis_shubhkarman_102303661/main.py
topsis_shubhkarman_102303661-1.0.2.dist-info/licenses/LICENSE
topsis_shubhkarman_102303661-1.0.2.dist-info/METADATA
topsis_shubhkarman_102303661-1.0.2.dist-info/WHEEL
topsis_shubhkarman_102303661-1.0.2.dist-info/entry_points.txt
topsis_shubhkarman_102303661-1.0.2.dist-info/top_level.txt
topsis_shubhkarman_102303661-1.0.2.dist-info/RECORD
