Metadata-Version: 2.4
Name: topsis-shubhkarman-102303661
Version: 1.0.2
Summary: A command-line implementation of TOPSIS for multi-criteria decision making
Author: Shubhkarman Singh
License-File: LICENSE
Requires-Dist: pandas
Requires-Dist: numpy
Dynamic: author
Dynamic: description
Dynamic: description-content-type
Dynamic: license-file
Dynamic: requires-dist
Dynamic: summary
